[
    {
        "date": "07/12/2022 - 19:00h às 21:00h - Sessão Solene",
        "event": "Solene: Medalha de Honra ao Mérito Braz Cubas ao Sr. Leonardo Barbosa Delfino",
        "local": "Plenário Dr. Oswaldo de Rosis - Castelinho - Praça Tenente Mauro Batista de Miranda, 01 - Vila Nova"
    },
    {
        "date": "08/12/2022 - 16:00h às 18:00h - Sessão Ordinária",
        "event": "Sessão Ordinária",
        "local": "Plenário Dr. Oswaldo de Rosis - Castelinho - Praça Tenente Mauro Batista de Miranda, 01 - Vila Nova"
    },
    {
        "date": "07/12/2022 - 19:00h às 21:00h - Sessão Solene",
        "event": "Solene: Medalha de Honra ao Mérito Braz Cubas ao Sr. Leonardo Barbosa Delfino",
        "local": "Plenário Dr. Oswaldo de Rosis - Castelinho - Praça Tenente Mauro Batista de Miranda, 01 - Vila Nova"
    },
    {
        "date": "08/12/2022 - 16:00h às 18:00h - Sessão Ordinária",
        "event": "Sessão Ordinária",
        "local": "Plenário Dr. Oswaldo de Rosis - Castelinho - Praça Tenente Mauro Batista de Miranda, 01 - Vila Nova"
    },
    {
        "date": "07/12/2022 - 19:00h às 21:00h - Sessão Solene",
        "event": "Solene: Medalha de Honra ao Mérito Braz Cubas ao Sr. Leonardo Barbosa Delfino",
        "local": "Plenário Dr. Oswaldo de Rosis - Castelinho - Praça Tenente Mauro Batista de Miranda, 01 - Vila Nova"
    },
    {
        "date": "08/12/2022 - 16:00h às 18:00h - Sessão Ordinária",
        "event": "Sessão Ordinária",
        "local": "Plenário Dr. Oswaldo de Rosis - Castelinho - Praça Tenente Mauro Batista de Miranda, 01 - Vila Nova"
    },
    {
        "date": "07/12/2022 - 19:00h às 21:00h - Sessão Solene",
        "event": "Solene: Medalha de Honra ao Mérito Braz Cubas ao Sr. Leonardo Barbosa Delfino",
        "local": "Plenário Dr. Oswaldo de Rosis - Castelinho - Praça Tenente Mauro Batista de Miranda, 01 - Vila Nova"
    },
    {
        "date": "08/12/2022 - 16:00h às 18:00h - Sessão Ordinária",
        "event": "Sessão Ordinária",
        "local": "Plenário Dr. Oswaldo de Rosis - Castelinho - Praça Tenente Mauro Batista de Miranda, 01 - Vila Nova"
    }
]